edusign/__init__.py
edusign/utils.py
edusign/models/__init__.py
edusign/models/courses.py
edusign/models/groups.py
edusign/models/professors.py
edusign/models/students.py
edusign-0.0.11.dist-info/LICENSE
edusign-0.0.11.dist-info/METADATA
edusign-0.0.11.dist-info/WHEEL
edusign-0.0.11.dist-info/top_level.txt
edusign-0.0.11.dist-info/RECORD
