Metadata-Version: 2.1
Name: edusign
Version: 0.0.11
Summary: Python client for Edusign (https://edusign.fr)
Home-page: https://github.com/seluj78/edusign
Author: Jules Lasne
Author-email: jules.lasne@gmail.com
License: GNU GPL 3
Project-URL: Changelog, https://github.com/Seluj78/edusign/commits/main
Classifier: Development Status :: 5 - Production/Stable
Classifier: Environment :: Web Environment
Classifier: Intended Audience :: Developers
Classifier: License :: OSI Approved :: BSD License
Classifier: Operating System :: OS Independent
Classifier: Programming Language :: Python :: 3.8
Classifier: Programming Language :: Python :: 3.9
Classifier: Programming Language :: Python :: 3.10
Classifier: Topic :: Software Development :: Libraries :: Python Modules
License-File: LICENSE
Requires-Dist: requests (>=2.0.0)
